Hockey/__main__.py
Hockey/config.py
Hockey/video.py
Hockey-0.1.3.dist-info/METADATA
Hockey-0.1.3.dist-info/RECORD
Hockey-0.1.3.dist-info/WHEEL
Hockey-0.1.3.dist-info/entry_points.txt
Hockey-0.1.3.dist-info/pbr.json
Hockey-0.1.3.dist-info/top_level.txt
